pyecsim.cpython-37m-x86_64-linux-gnu.so
pyecsim-0.2.3.post2.dist-info/LICENSE
pyecsim-0.2.3.post2.dist-info/RECORD
pyecsim-0.2.3.post2.dist-info/WHEEL
pyecsim-0.2.3.post2.dist-info/METADATA
pyecsim-0.2.3.post2.dist-info/top_level.txt
